LICENSE.txt
README.md
setup.py
leogeogridding/__init__.py
leogeogridding/fileparser.py
leogeogridding/filter_data.py
leogeogridding/grid_ncf.py
leogeogridding/gridding.py
leogeogridding/gtools.py
leogeogridding/naming_conventions.py
leogeogridding/sat_data_input.py
leogeogridding/solar_zenith.py
leogeogridding/time_conv.py
leogeogridding.egg-info/PKG-INFO
leogeogridding.egg-info/SOURCES.txt
leogeogridding.egg-info/dependency_links.txt
leogeogridding.egg-info/entry_points.txt
leogeogridding.egg-info/requires.txt
leogeogridding.egg-info/top_level.txt