Metadata-Version: 2.1
Name: leogeogridding
Version: 0.0.1
Summary: Data fusion package for transforming L2 satellite to L3 spatial-temporal gridded data
Home-page: https://github.com/pkv0/leogeo-gridding
Author: Sally Zhao, Neil Gutkin
Author-email: v.kiliyanpilakkil@gmail.com
License: MIT
Keywords: data fusion,satellite,L2,L3
Classifier: Development Status :: 3 - Alpha
Classifier: Intended Audience :: Developers
Classifier: Topic :: Software Development :: Build Tools
Classifier: License :: OSI Approved :: MIT License
Classifier: Programming Language :: Python :: 3
Classifier: Programming Language :: Python :: 3.4
Classifier: Programming Language :: Python :: 3.5
Classifier: Programming Language :: Python :: 3.6
Classifier: Programming Language :: Python :: 3.7
Classifier: Programming Language :: Python :: 3.8
License-File: LICENSE.txt
